defradb/__init__.py
defradb/defradb.py
defradb/rpc/api_pb2.py
defradb/rpc/api_pb2_grpc.py
defradb-0.1.3.dist-info/METADATA
defradb-0.1.3.dist-info/WHEEL
defradb-0.1.3.dist-info/licenses/LICENSE
defradb-0.1.3.dist-info/RECORD
