Metadata-Version: 2.1
Name: defradb
Version: 0.1.3
Summary: DefraDB Python client
Project-URL: Homepage, https://github.com/sourcenetwork/defradb-client-py
Project-URL: Bug Tracker, https://github.com/sourcenetwork/defradb-client-py/issues
Author-email: Orpheus Lummis <o@orpheuslummis.info>
License: MIT
License-File: LICENSE
Classifier: License :: OSI Approved :: MIT License
Classifier: Programming Language :: Python :: 3
Classifier: Topic :: Database
Requires-Python: >=3.10
Requires-Dist: aiohttp~=3.8
Requires-Dist: gql~=3.5.0b3
Requires-Dist: grpcio-tools~=1.54.0
Requires-Dist: grpcio~=1.54.0
Requires-Dist: multiaddr~=0.0.9
Requires-Dist: requests-toolbelt~=0.10.1
Requires-Dist: requests~=2.29.0
